setup.py
django_geoware.egg-info/PKG-INFO
django_geoware.egg-info/SOURCES.txt
django_geoware.egg-info/dependency_links.txt
django_geoware.egg-info/requires.txt
django_geoware.egg-info/top_level.txt
geoware/__init__.py
geoware/apps.py
geoware/urls.py
geoware/__pycache__/__init__.cpython-34.pyc
geoware/__pycache__/apps.cpython-34.pyc
geoware/__pycache__/urls.cpython-34.pyc
geoware/admin/__init__.py
geoware/admin/altname.py
geoware/admin/city.py
geoware/admin/continent.py
geoware/admin/country.py
geoware/admin/currency.py
geoware/admin/division.py
geoware/admin/language.py
geoware/admin/ocean.py
geoware/admin/subdivision.py
geoware/admin/timezone.py
geoware/admin/__pycache__/__init__.cpython-34.pyc
geoware/admin/__pycache__/altname.cpython-34.pyc
geoware/admin/__pycache__/city.cpython-34.pyc
geoware/admin/__pycache__/continent.cpython-34.pyc
geoware/admin/__pycache__/country.cpython-34.pyc
geoware/admin/__pycache__/currency.cpython-34.pyc
geoware/admin/__pycache__/district.cpython-34.pyc
geoware/admin/__pycache__/division.cpython-34.pyc
geoware/admin/__pycache__/language.cpython-34.pyc
geoware/admin/__pycache__/ocean.cpython-34.pyc
geoware/admin/__pycache__/region.cpython-34.pyc
geoware/admin/__pycache__/subdivision.cpython-34.pyc
geoware/admin/__pycache__/subregion.cpython-34.pyc
geoware/admin/__pycache__/timezone.cpython-34.pyc
geoware/defaults/__init__.py
geoware/defaults/city.py
geoware/defaults/common.py
geoware/defaults/continent.py
geoware/defaults/country.py
geoware/defaults/currency.py
geoware/defaults/division.py
geoware/defaults/language.py
geoware/defaults/ocean.py
geoware/defaults/__pycache__/__init__.cpython-34.pyc
geoware/defaults/__pycache__/city.cpython-34.pyc
geoware/defaults/__pycache__/common.cpython-34.pyc
geoware/defaults/__pycache__/continent.cpython-34.pyc
geoware/defaults/__pycache__/country.cpython-34.pyc
geoware/defaults/__pycache__/currency.cpython-34.pyc
geoware/defaults/__pycache__/division.cpython-34.pyc
geoware/defaults/__pycache__/language.cpython-34.pyc
geoware/defaults/__pycache__/ocean.cpython-34.pyc
geoware/defaults/__pycache__/region.cpython-34.pyc
geoware/forms/__init__.py
geoware/forms/altname.py
