Metadata-Version: 1.1
Name: django-geoware
Version: 0.1.0
Summary: A Django application for handling GIS related data.
Home-page: https://github.com/un33k/django-geoware
Author: Val Neekman
Author-email: info@neekware.com
License: BSD
Platform: UNKNOWN
Classifier: Development Status :: 4 - Beta
Classifier: Environment :: Web Environment
Classifier: Intended Audience :: Developers
Classifier: License :: OSI Approved :: MIT License
Classifier: Operating System :: OS Independent
Classifier: Programming Language :: Python
Classifier: Programming Language :: Python :: 3.4
Classifier: Programming Language :: Python :: 3.5
Classifier: Topic :: Utilities
